__init__.py
doc2ann.py
fix_docstring.py
runner.py
test/__init__.py
test/test_doc2ann.py
test/fixtures/functions_with_comments.py
test/fixtures/method_and_func.py
test/fixtures/module_ann.py
doc2ann-0.2.0.dist-info/LICENSE
doc2ann-0.2.0.dist-info/METADATA
doc2ann-0.2.0.dist-info/WHEEL
doc2ann-0.2.0.dist-info/entry_points.txt
doc2ann-0.2.0.dist-info/top_level.txt
doc2ann-0.2.0.dist-info/RECORD
